pure_checker.cpython-310-x86_64-linux-gnu.so
pure_checker-2.1.dist-info/AUTHORS
pure_checker-2.1.dist-info/WHEEL
pure_checker-2.1.dist-info/LICENSE
pure_checker-2.1.dist-info/RECORD
pure_checker-2.1.dist-info/METADATA
pure_checker-2.1.dist-info/top_level.txt
