Metadata-Version: 2.1
Name: pure-checker
Version: 2.1
Summary: A static analysis file format checker.
Author: Joran Dirk Greef (Ronomon), Maxim Vainstein (Microsoft), Milind Solage (Microsoft), Patrik Vicol (Microsoft), Stacy Sheperson (Microsoft)
Maintainer-email: Seb <me@sebjo.se>
License: The MIT License (MIT)
Requires-Python: >=3.9
License-File: LICENSE
License-File: AUTHORS
